vexcogutils/__init__.py
vexcogutils/chat.py
vexcogutils/consts.py
vexcogutils/loop.py
vexcogutils/meta.py
vexcogutils/py.typed
vexcogutils/sentry.py
vexcogutils/sqldriver.py
vexcogutils/version.py
vex_cog_utils-1.5.9.dist-info/LICENSE
vex_cog_utils-1.5.9.dist-info/METADATA
vex_cog_utils-1.5.9.dist-info/WHEEL
vex_cog_utils-1.5.9.dist-info/top_level.txt
vex_cog_utils-1.5.9.dist-info/RECORD
