Metadata-Version: 2.1
Name: vex-cog-utils
Version: 1.5.9
Summary: Utility functions for the Vex-Cogs repo.
Home-page: https://github.com/Vexed01/vex-cog-utils
Author: Vexed01
Author-email: gh.vexed@gmail.com
License: UNKNOWN
Platform: UNKNOWN
Classifier: License :: OSI Approved :: MIT License
Classifier: Programming Language :: Python :: 3.8
Classifier: Operating System :: OS Independent
Requires-Python: >=3.8.1
Requires-Dist: tabulate
Requires-Dist: sentry-sdk
Requires-Dist: cachetools
Requires-Dist: asyncache
